Workbook
Name SlicerCache_Table_1_Col_3: #N/A

Sheet Raw_Data
A1: Campaign_ID | B1: Date | C1: Channel | D1: Campaign_Name | E1: Impressions | F1: Clicks | G1: Spend_USD | H1: Conversions | I1: Revenue_USD | J1: ROAS
A2: CAMP-5001 | B2: 46023 | C2: Google Ads | D2: Q1 Search Growth | E2: 45200 | F2: 1820 | G2: 1250 | H2: 95 | I2: 4850 | J2: =VALUE(I2)/VALUE(G2) -> 3.88
A3: CAMP-5002 | B3: 46024 | C3: Meta Ads | D3: Brand Awareness Retargeting | E3: 89000 | F3: 3100 | G3: 2100 | H3: 110 | I3: 6300 | J3: =VALUE(I3)/VALUE(G3) -> 3
A4: CAMP-5003 | B4: 46025 | C4: LinkedIn | D4: B2B Lead Gen Q1 | E4: 18500 | F4: 620 | G4: 1400 | H4: 42 | I4: 5600 | J4: =VALUE(I4)/VALUE(G4) -> 4
A5: CAMP-5004 | B5: 46026 | C5: YouTube | D5: Product Demo Video Ad | E5: 125000 | F5: 4500 | G5: 3200 | H5: 150 | I5: 9600 | J5: =VALUE(I5)/VALUE(G5) -> 3
A6: CAMP-5005 | B6: 46027 | C6: Email | D6: Weekly Newsletter Promo | E6: 25000 | F6: 2200 | G6: 350 | H6: 185 | I6: 4200 | J6: =VALUE(I6)/VALUE(G6) -> 12
A7: CAMP-5006 | B7: 46028 | C7: Google Ads | D7: Competitor Keyword Target | E7: 38000 | F7: 1450 | G7: 1100 | H7: 72 | I7: 3960 | J7: =VALUE(I7)/VALUE(G7) -> 3.6
A8: CAMP-5007 | B8: 46029 | C8: Meta Ads | D8: Lookalike Audience Spring | E8: 74000 | F8: 2800 | G8: 1950 | H8: 98 | I8: 5850 | J8: =VALUE(I8)/VALUE(G8) -> 3
A9: CAMP-5008 | B9: 46030 | C9: LinkedIn | D9: Enterprise Software Pitch | E9: 21000 | F9: 710 | G9: 1650 | H9: 51 | I9: 7425 | J9: =VALUE(I9)/VALUE(G9) -> 4.5
A10: CAMP-5009 | B10: 46031 | C10: YouTube | D10: Client Testimonial Spot | E10: 95000 | F10: 3400 | G10: 2500 | H10: 115 | I10: 7750 | J10: =VALUE(I10)/VALUE(G10) -> 3.1
A11: CAMP-5010 | B11: 46032 | C11: Email | D11: Flash Sale Announcement | E11: 28000 | F11: 2600 | G11: 400 | H11: 210 | I11: 5250 | J11: =VALUE(I11)/VALUE(G11) -> 13.125
A12: CAMP-5011 | B12: 46033 | C12: Google Ads | D12: Brand Protection | E12: 51000 | F12: 2100 | G12: 1350 | H12: 105 | I12: 5400 | J12: =VALUE(I12)/VALUE(G12) -> 4
A13: CAMP-5012 | B13: 46034 | C13: Meta Ads | D13: Carousel Showcase | E13: 68000 | F13: 2450 | G13: 1700 | H13: 88 | I13: 4930 | J13: =VALUE(I13)/VALUE(G13) -> 2.9
... A101: CAMP-5100 | B101: 46132 | C101: Email | D101: April Final Blast | E101: 32500 | F101: 3150 | G101: 510 | H101: 275 | I101: 7975 | J101: =VALUE(I101)/VALUE(G101) -> 15.637255

Sheet Pivot_Engine
A1: Channel | B1: Total_Impressions | C1: Total_Clicks | D1: Total_Spend_USD | E1: Total_Conversions | F1: Total_Revenue_USD | G1: Blended_ROAS
A2: Google Ads | B2: =SUMIF(Raw_Data!$C$2:$C$101, A2, Raw_Data!$E$2:$E$101) -> 921200 | C2: =SUMIF(Raw_Data!$C$2:$C$101, A2, Raw_Data!$F$2:$F$101) -> 36880 | D2: =SUMIF(Raw_Data!$C$2:$C$101, A2, Raw_Data!$G$2:$G$101) -> 25555 | E2: =SUMIF(Raw_Data!$C$2:$C$101, A2, Raw_Data!$H$2:$H$101) -> 1898 | F2: =SUMIF(Raw_Data!$C$2:$C$101, A2, Raw_Data!$I$2:$I$101) -> 106911 | G2: =IF(D2=0, 0, F2/D2) -> 4.1835649
A3: Meta Ads | B3: =SUMIF(Raw_Data!$C$2:$C$101, A3, Raw_Data!$E$2:$E$101) -> 1659000 | C3: =SUMIF(Raw_Data!$C$2:$C$101, A3, Raw_Data!$F$2:$F$101) -> 59280 | D3: =SUMIF(Raw_Data!$C$2:$C$101, A3, Raw_Data!$G$2:$G$101) -> 40320 | E3: =SUMIF(Raw_Data!$C$2:$C$101, A3, Raw_Data!$H$2:$H$101) -> 2115 | F3: =SUMIF(Raw_Data!$C$2:$C$101, A3, Raw_Data!$I$2:$I$101) -> 126233 | G3: =IF(D3=0, 0, F3/D3) -> 3.1307788
A4: Linkdin | B4: =SUMIF(Raw_Data!$C$2:$C$101, A4, Raw_Data!$E$2:$E$101) -> 0 | C4: =SUMIF(Raw_Data!$C$2:$C$101, A4, Raw_Data!$F$2:$F$101) -> 0 | D4: =SUMIF(Raw_Data!$C$2:$C$101, A4, Raw_Data!$G$2:$G$101) -> 0 | E4: =SUMIF(Raw_Data!$C$2:$C$101, A4, Raw_Data!$H$2:$H$101) -> 0 | F4: =SUMIF(Raw_Data!$C$2:$C$101, A4, Raw_Data!$I$2:$I$101) -> 0 | G4: =IF(D4=0, 0, F4/D4) -> 0
A5: Youtube | B5: =SUMIF(Raw_Data!$C$2:$C$101, A5, Raw_Data!$E$2:$E$101) -> 2131000 | C5: =SUMIF(Raw_Data!$C$2:$C$101, A5, Raw_Data!$F$2:$F$101) -> 76460 | D5: =SUMIF(Raw_Data!$C$2:$C$101, A5, Raw_Data!$G$2:$G$101) -> 55180 | E5: =SUMIF(Raw_Data!$C$2:$C$101, A5, Raw_Data!$H$2:$H$101) -> 2579 | F5: =SUMIF(Raw_Data!$C$2:$C$101, A5, Raw_Data!$I$2:$I$101) -> 172995 | G5: =IF(D5=0, 0, F5/D5) -> 3.1351033
A6: Email | B6: =SUMIF(Raw_Data!$C$2:$C$101, A6, Raw_Data!$E$2:$E$101) -> 570000 | C6: =SUMIF(Raw_Data!$C$2:$C$101, A6, Raw_Data!$F$2:$F$101) -> 51700 | D6: =SUMIF(Raw_Data!$C$2:$C$101, A6, Raw_Data!$G$2:$G$101) -> 8295 | E6: =SUMIF(Raw_Data!$C$2:$C$101, A6, Raw_Data!$H$2:$H$101) -> 4380 | F6: =SUMIF(Raw_Data!$C$2:$C$101, A6, Raw_Data!$I$2:$I$101) -> 114124 | G6: =IF(D6=0, 0, F6/D6) -> 13.758168

Sheet Dashboard
A1: OPERATIONAL KPI & MARKETING METRIC BOARD
A3: Real-Time Multi-Channel Marketing Performance Intelligence
A5: TOTAL AD SPEND | C5: TOTAL REVENUE | E5: BLENDED ROAS | G5: TOTAL CONVERSIONS
A6: =SUM(Raw_Data!G2:G101) -> 162450 | C6: =SUM(Raw_Data!I2:I101) -> 673703 | E6: =IF(A6=0, 0, C6/A6) -> 4.1471407 | G6: =SUM(Raw_Data!H2:H101) -> 12030

Sheet Lookup & Reference
A1: Channel | B1: Target_ROAS | C1: Max_Monthly_Budget_USD | D1: Assigned_Manager
A2: Google Ads | B2: 3.5 | C2: 15000 | D2: Sarah Jenkins
A3: Meta Ads | B3: 2.8 | C3: 12000 | D3: Alex Rivera
A4: LinkedIn | B4: 4 | C4: 10000 | D4: Marcus Vance
A5: YouTube | B5: 3 | C5: 20000 | D5: Elena Rostova
A6: Email | B6: 5 | C6: 3000 | D6: David Kim
